segmetrics/__init__.py
imgmetrics-0.0.1.dist-info/LICENSE
imgmetrics-0.0.1.dist-info/METADATA
imgmetrics-0.0.1.dist-info/WHEEL
imgmetrics-0.0.1.dist-info/top_level.txt
imgmetrics-0.0.1.dist-info/RECORD
